sxd_core/__init__.py
sxd_core/arrow.py
sxd_core/audit.py
sxd_core/auth.py
sxd_core/chdb_client.py
sxd_core/clickhouse.py
sxd_core/config.py
sxd_core/data_layer.py
sxd_core/exceptions.py
sxd_core/io.py
sxd_core/logging.py
sxd_core/registry.py
sxd_core/storage.py
sxd_core/worker.py
sxd_core/worker_upload.py
sxd_core-0.1.0.dist-info/METADATA
sxd_core-0.1.0.dist-info/WHEEL
sxd_core-0.1.0.dist-info/top_level.txt
sxd_core-0.1.0.dist-info/RECORD
